carmine-0.1.4.dist-info/METADATA
carmine-0.1.4.dist-info/WHEEL
carmine-0.1.4.dist-info/entry_points.txt
carmine-0.1.4.dist-info/licenses/COPYING
carmine-0.1.4.dist-info/licenses/LICENSES/Apache-2.0.txt
carmine-0.1.4.dist-info/licenses/LICENSES/CC-BY-4.0.txt
carmine-0.1.4.dist-info/licenses/LICENSES/CC-BY-SA-4.0.txt
carmine-0.1.4.dist-info/licenses/LICENSES/LicenseRef-DCO-1.1-license.txt
carmine/__init__.py
carmine/cli.py
carmine-0.1.4.dist-info/RECORD
