Metadata-Version: 2.1
Name: carmine
Version: 0.1.4
Summary: An opinionated Python toolchain made by crushing bugs.
Author-Email: David Seaward <david@librem.one>
License: Apache-2.0
Project-URL: Source, https://gitlab.com/lfdo/toolchain/carmine
Project-URL: Project, https://lofidevops.neocities.org
Requires-Python: >=3.10
Requires-Dist: black~=23.0
Requires-Dist: coverage>=7.2.1
Requires-Dist: mdformat>=0.7.16
Requires-Dist: mdformat_mkdocs[recommended]>=1.0.0
Requires-Dist: mkdocs>=1.4.2
Requires-Dist: mkdocs-awesome-pages-plugin>=2.8.0
Requires-Dist: mkdocs-mermaid2-plugin>=0.6.0
Requires-Dist: pytest>=7.2.2
Requires-Dist: reuse>=1.1.2
